uptimes/__init__.py
uptimes/uptimes.py
uptimes-1.0.0.dist-info/LICENSE
uptimes-1.0.0.dist-info/METADATA
uptimes-1.0.0.dist-info/WHEEL
uptimes-1.0.0.dist-info/top_level.txt
uptimes-1.0.0.dist-info/RECORD
