Metadata-Version: 2.1
Name: uptimes
Version: 1.0.0
Summary: A small python3 package for uptimes.
Home-page: https://github.com/Tim232/Uptimes
Author: Tim232
Author-email: endbot4023@gmail.com
License: MIT
Download-URL: https://github.com/Tim232/Uptimes
Keywords: easyuptime,uptimes
Platform: UNKNOWN
Classifier: Programming Language :: Python :: 3
Classifier: License :: OSI Approved :: MIT License
Classifier: Development Status :: 5 - Production/Stable
Classifier: Operating System :: OS Independent
Requires-Python: >=3
